[{"inputs":[],"stateMutability":"nonpayable","type":"constructor"},{"anonymous":false,"inputs":[{"indexed":false,"internalType":"address","name":"owner","type":"address"},{"indexed":false,"internalType":"bytes32","name":"desciription","type":"bytes32"},{"indexed":false,"internalType":"uint256","name":"created_at","type":"uint256"}],"name":"logginEvent","type":"event"},{"anonymous":false,"inputs":[{"indexed":false,"internalType":"address","name":"owner","type":"address"},{"indexed":false,"internalType":"address","name":"to","type":"address"},{"indexed":false,"internalType":"string","name":"product_id","type":"string"},{"indexed":false,"internalType":"string","name":"metadata","type":"string"},{"indexed":false,"internalType":"string","name":"status","type":"string"},{"indexed":false,"internalType":"string","name":"note","type":"string"},{"indexed":false,"internalType":"uint256","name":"created_at","type":"uint256"}],"name":"productTransaction","type":"event"},{"anonymous":false,"inputs":[{"indexed":false,"internalType":"address","name":"owner","type":"address"},{"indexed":false,"internalType":"string","name":"role","type":"string"},{"indexed":false,"internalType":"string","name":"name","type":"string"},{"indexed":false,"internalType":"uint256","name":"created_at","type":"uint256"}],"name":"registerAction","type":"event"},{"anonymous":false,"inputs":[{"indexed":false,"internalType":"address","name":"owner","type":"address"},{"indexed":false,"internalType":"string","name":"action","type":"string"},{"indexed":false,"internalType":"string","name":"name","type":"string"},{"indexed":false,"internalType":"uint256","name":"created_at","type":"uint256"}],"name":"userInteraction","type":"event"},{"inputs":[{"internalType":"string","name":"","type":"string"},{"internalType":"uint256","name":"","type":"uint256"}],"name":"_permission","outputs":[{"internalType":"string","name":"","type":"string"}],"stateMutability":"view","type":"function","constant":true},{"inputs":[{"internalType":"address","name":"","type":"address"}],"name":"name","outputs":[{"internalType":"string","name":"","type":"string"}],"stateMutability":"view","type":"function","constant":true},{"inputs":[],"name":"owner","outputs":[{"internalType":"address","name":"","type":"address"}],"stateMutability":"view","type":"function","constant":true},{"inputs":[{"internalType":"address","name":"","type":"address"},{"internalType":"uint256","name":"","type":"uint256"}],"name":"products","outputs":[{"internalType":"string","name":"id","type":"string"},{"internalType":"address","name":"owner","type":"address"},{"internalType":"address","name":"created_by","type":"address"},{"internalType":"string","name":"status","type":"string"},{"internalType":"string","name":"metadata","type":"string"},{"internalType":"uint256","name":"created_at","type":"uint256"}],"stateMutability":"view","type":"function","constant":true},{"inputs":[{"internalType":"address","name":"","type":"address"}],"name":"profile","outputs":[{"internalType":"address","name":"id","type":"address"},{"internalType":"bool","name":"is_login","type":"bool"},{"internalType":"string","name":"role","type":"string"},{"internalType":"string","name":"name","type":"string"}],"stateMutability":"view","type":"function","constant":true},{"inputs":[{"internalType":"address","name":"user_id","type":"address"}],"name":"checkLoginStatus","outputs":[{"internalType":"bool","name":"","type":"bool"}],"stateMutability":"view","type":"function","constant":true},{"inputs":[{"internalType":"address","name":"user_id","type":"address"}],"name":"checkRegisterStatus","outputs":[{"internalType":"bool","name":"","type":"bool"}],"stateMutability":"view","type":"function","constant":true},{"inputs":[],"name":"login","outputs":[{"internalType":"bool","name":"","type":"bool"}],"stateMutability":"nonpayable","type":"function"},{"inputs":[{"internalType":"address","name":"_id","type":"address"}],"name":"changeUserStatus","outputs":[],"stateMutability":"nonpayable","type":"function"},{"inputs":[{"internalType":"string","name":"_name","type":"string"},{"internalType":"string","name":"_role","type":"string"}],"name":"register","outputs":[{"internalType":"bool","name":"","type":"bool"}],"stateMutability":"nonpayable","type":"function"},{"inputs":[{"internalType":"address","name":"_id","type":"address"}],"name":"profileInformation","outputs":[{"components":[{"internalType":"address","name":"id","type":"address"},{"internalType":"bool","name":"is_login","type":"bool"},{"internalType":"string","name":"role","type":"string"},{"internalType":"string","name":"name","type":"string"}],"internalType":"struct Magang.ProfileStruct","name":"","type":"tuple"}],"stateMutability":"view","type":"function","constant":true},{"inputs":[{"internalType":"string","name":"_id","type":"string"},{"internalType":"string","name":"metadata","type":"string"}],"name":"createProduct","outputs":[{"internalType":"bool","name":"","type":"bool"}],"stateMutability":"nonpayable","type":"function"},{"inputs":[{"internalType":"address","name":"_id","type":"address"}],"name":"getListProducts","outputs":[{"components":[{"internalType":"string","name":"id","type":"string"},{"internalType":"address","name":"owner","type":"address"},{"internalType":"address","name":"created_by","type":"address"},{"internalType":"string","name":"status","type":"string"},{"internalType":"string","name":"metadata","type":"string"},{"internalType":"uint256","name":"created_at","type":"uint256"}],"internalType":"struct Magang.ProductStruct[]","name":"","type":"tuple[]"}],"stateMutability":"view","type":"function","constant":true},{"inputs":[],"name":"getOwner","outputs":[{"internalType":"address","name":"","type":"address"}],"stateMutability":"view","type":"function","constant":true},{"inputs":[],"name":"getAllRoles","outputs":[{"components":[{"internalType":"string","name":"name","type":"string"},{"internalType":"string[]","name":"permission","type":"string[]"}],"internalType":"struct Magang.PermissionStruct[]","name":"","type":"tuple[]"}],"stateMutability":"view","type":"function","constant":true},{"inputs":[{"internalType":"string","name":"_name","type":"string"}],"name":"getPermissionByName","outputs":[{"internalType":"string[]","name":"","type":"string[]"}],"stateMutability":"view","type":"function","constant":true},{"inputs":[],"name":"getUsers","outputs":[{"components":[{"internalType":"address","name":"id","type":"address"},{"internalType":"bool","name":"is_login","type":"bool"},{"internalType":"string","name":"role","type":"string"},{"internalType":"string","name":"name","type":"string"}],"internalType":"struct Magang.ProfileStruct[]","name":"","type":"tuple[]"}],"stateMutability":"view","type":"function","constant":true},{"inputs":[{"internalType":"address","name":"to","type":"address"},{"internalType":"string","name":"product_id","type":"string"},{"internalType":"string","name":"note","type":"string"},{"internalType":"string","name":"metadata","type":"string"}],"name":"sendProduct","outputs":[{"internalType":"bool","name":"","type":"bool"}],"stateMutability":"nonpayable","type":"function"},{"inputs":[{"internalType":"address","name":"prev_owner","type":"address"},{"internalType":"string","name":"product_id","type":"string"},{"internalType":"string","name":"note","type":"string"},{"internalType":"string","name":"metadata","type":"string"}],"name":"confirmationProduct","outputs":[{"internalType":"bool","name":"","type":"bool"}],"stateMutability":"nonpayable","type":"function"},{"inputs":[{"internalType":"address","name":"sender","type":"address"}],"name":"isOwner","outputs":[{"internalType":"bool","name":"","type":"bool"}],"stateMutability":"view","type":"function","constant":true},{"inputs":[],"name":"getAllPermission","outputs":[{"internalType":"string[]","name":"","type":"string[]"}],"stateMutability":"view","type":"function","constant":true},{"inputs":[{"internalType":"string","name":"_role","type":"string"},{"internalType":"string[]","name":"permissions","type":"string[]"}],"name":"addRole","outputs":[{"internalType":"bool","name":"","type":"bool"}],"stateMutability":"nonpayable","type":"function"},{"inputs":[{"components":[{"internalType":"string","name":"id","type":"string"},{"internalType":"address","name":"owner","type":"address"},{"internalType":"address","name":"created_by","type":"address"},{"internalType":"string","name":"status","type":"string"},{"internalType":"string","name":"metadata","type":"string"},{"internalType":"uint256","name":"created_at","type":"uint256"}],"internalType":"struct Magang.ProductStruct[]","name":"oldArray","type":"tuple[]"}],"name":"mapArray","outputs":[],"stateMutability":"nonpayable","type":"function"},{"inputs":[{"internalType":"string","name":"product_id","type":"string"},{"internalType":"string","name":"note","type":"string"},{"internalType":"string","name":"metadata","type":"string"}],"name":"deleteProduct","outputs":[{"internalType":"bool","name":"","type":"bool"}],"stateMutability":"nonpayable","type":"function"},{"inputs":[{"internalType":"string","name":"product_id","type":"string"},{"internalType":"string","name":"metadata","type":"string"}],"name":"updateProduct","outputs":[{"internalType":"bool","name":"","type":"bool"}],"stateMutability":"nonpayable","type":"function"},{"inputs":[{"internalType":"address","name":"_sender","type":"address"}],"name":"getPermission","outputs":[{"internalType":"string[]","name":"","type":"string[]"}],"stateMutability":"view","type":"function","constant":true},{"inputs":[{"internalType":"address","name":"_sender","type":"address"},{"internalType":"string","name":"_permissions","type":"string"}],"name":"addPermission","outputs":[{"internalType":"bool","name":"","type":"bool"}],"stateMutability":"nonpayable","type":"function"}]